jsonvaluetester/__init__.py
jsonvaluetester/api_helper.py
jsonvaluetester/configuration.py
jsonvaluetester/jsonvaluetester_client.py
jsonvaluetester/controllers/__init__.py
jsonvaluetester/controllers/base_controller.py
jsonvaluetester/controllers/json_obj_controller.py
jsonvaluetester/controllers/json_val_controller.py
jsonvaluetester/exceptions/__init__.py
jsonvaluetester/exceptions/api_exception.py
jsonvaluetester/http/__init__.py
jsonvaluetester/http/http_call_back.py
jsonvaluetester/http/http_method_enum.py
jsonvaluetester/http/http_request.py
jsonvaluetester/http/http_response.py
jsonvaluetester/models/__init__.py
jsonvaluetester/models/content_type.py
jsonvaluetester/models/schema_container.py
jsonvaluetester/models/server_response.py
jsonvaluetester/models/value_container.py
jsonvaluetester/utilities/__init__.py
jsonvaluetester/utilities/file_wrapper.py
asad_14_json_generator-0.2.0.dist-info/LICENSE
asad_14_json_generator-0.2.0.dist-info/METADATA
asad_14_json_generator-0.2.0.dist-info/WHEEL
asad_14_json_generator-0.2.0.dist-info/top_level.txt
asad_14_json_generator-0.2.0.dist-info/RECORD
